src/__init__.py
src/my_recipe1.py
recipe_first_package-1.0.0.dist-info/METADATA
recipe_first_package-1.0.0.dist-info/WHEEL
recipe_first_package-1.0.0.dist-info/top_level.txt
recipe_first_package-1.0.0.dist-info/RECORD
