Metadata-Version: 2.1
Name: recipe-first-package
Version: 1.0.0
Summary: this package contains some sample recipe codes
Author: Dustin Baek
Author-email: dustinbaek@deloitte.co.uk
Requires-Dist: pandas
Requires-Dist: numpy
Requires-Dist: pytest
